lrcalc.cp310-win_arm64.pyd
lrcalc-2.1.data/platlib/liblrcalc-2-c2a08859181961212bc6f0b68588eab9.dll
lrcalc-2.1.dist-info/DELVEWHEEL
lrcalc-2.1.dist-info/METADATA
lrcalc-2.1.dist-info/RECORD
lrcalc-2.1.dist-info/top_level.txt
lrcalc-2.1.dist-info/WHEEL
lrcalc-2.1.dist-info/licenses/COPYING
lrcalc-2.1.dist-info/licenses/LICENSE
