Metadata-Version: 2.4
Name: lrcalc
Version: 2.1
Summary: Littlewood-Richardson Calculator bindings
Home-page: https://math.rutgers.edu/~asbuch/lrcalc
Author: Anders Skovsted Buch
License: GPL3
Requires-Python: >=3
License-File: LICENSE
License-File: COPYING
Dynamic: author
Dynamic: description
Dynamic: description-content-type
Dynamic: home-page
Dynamic: license
Dynamic: license-file
Dynamic: requires-python
Dynamic: summary
